poetry_jupyter_plugin/__init__.py
poetry_jupyter_plugin/assets/poetry.png
poetry_jupyter_plugin/assets/poetry.svg
poetry_jupyter_plugin/plugin.py
poetry_jupyter_plugin-0.2.2.dist-info/LICENSE.txt
poetry_jupyter_plugin-0.2.2.dist-info/METADATA
poetry_jupyter_plugin-0.2.2.dist-info/WHEEL
poetry_jupyter_plugin-0.2.2.dist-info/entry_points.txt
poetry_jupyter_plugin-0.2.2.dist-info/RECORD
