Metadata-Version: 2.3
Name: poetry-jupyter-plugin
Version: 0.2.2
Summary: Poetry plugin to manage Jupyter kernels
License: MIT
Keywords: poetry,poetry-plugin,plugin,jupyter,jupyter-kernel
Author: Patrick Kage
Author-email: patrick.r.kage@gmail.com
Requires-Python: >=3.10,<4.0
Classifier: Framework :: Jupyter
Classifier: License :: OSI Approved :: MIT License
Classifier: Programming Language :: Python :: 3
Classifier: Programming Language :: Python :: 3.10
Classifier: Programming Language :: Python :: 3.11
Classifier: Programming Language :: Python :: 3.12
Classifier: Programming Language :: Python :: 3.13
Classifier: Topic :: Scientific/Engineering
Classifier: Topic :: Software Development
Classifier: Topic :: Utilities
Requires-Dist: jupyter-client (>=7.4.8,<8.0.0)
Requires-Dist: poetry (>=2.0.0,<3.0.0)
Project-URL: Homepage, https://github.com/pkage/poetry-jupyter-plugin
Project-URL: Repository, https://github.com/pkage/poetry-jupyter-plugin
